src/__init__.py
src/config/__init__.py
src/config/data_config.py
src/config/model_config.py
src/data/__init__.py
src/data/make_dataset.py
src/models/__init__.py
src/models/train_model.py
src/models/validate_model.py
src/tests/__init__.py
src/tests/model_accuracy_test.py
src/tests/model_type_test.py
hekaido_hw5_repo-0.1.0.dist-info/LICENSE
hekaido_hw5_repo-0.1.0.dist-info/METADATA
hekaido_hw5_repo-0.1.0.dist-info/WHEEL
hekaido_hw5_repo-0.1.0.dist-info/top_level.txt
hekaido_hw5_repo-0.1.0.dist-info/RECORD
